merql-0.0.2.dist-info/METADATA
merql-0.0.2.dist-info/WHEEL
merql/__init__.py
merql-0.0.2.dist-info/RECORD
